av98/__init__.py
av98/cache.py
av98/certmanager.py
av98/client.py
av98/main.py
av98/tofu.py
av98/util.py
AV_98-1.1.0.dist-info/LICENSE
AV_98-1.1.0.dist-info/METADATA
AV_98-1.1.0.dist-info/WHEEL
AV_98-1.1.0.dist-info/entry_points.txt
AV_98-1.1.0.dist-info/top_level.txt
AV_98-1.1.0.dist-info/RECORD
